CHANGES.rst
MANIFEST.in
README.rst
setup.cfg
setup.py
docs/LICENSE.GPL
docs/LICENSE.rst
docs/index.rst
src/collective/__init__.py
src/collective.contentcreator.egg-info/PKG-INFO
src/collective.contentcreator.egg-info/SOURCES.txt
src/collective.contentcreator.egg-info/dependency_links.txt
src/collective.contentcreator.egg-info/namespace_packages.txt
src/collective.contentcreator.egg-info/not-zip-safe
src/collective.contentcreator.egg-info/requires.txt
src/collective.contentcreator.egg-info/top_level.txt
src/collective/contentcreator/__init__.py