Metadata-Version: 1.1
Name: collective.contentcreator
Version: 1.0
Summary: Create content structures from JSON configurations
Home-page: https://pypi.python.org/pypi/collective.contentcreator
Author: Johannes Raggam
Author-email: thetetet@gmail.com
License: GPL version 2
Keywords: Python Plone
Platform: UNKNOWN
Classifier: Environment :: Web Environment
Classifier: Framework :: Plone
Classifier: Framework :: Plone :: 5.0
Classifier: Programming Language :: Python
Classifier: Programming Language :: Python :: 2.7
Classifier: Operating System :: OS Independent
Classifier: License :: OSI Approved :: GNU General Public License v2 (GPLv2)
